LICENSE
MANIFEST.in
README.rst
setup.cfg
setup.py
doc/Makefile
doc/architecture.rst
doc/conf.py
doc/features.rst
doc/index.rst
doc/installing.rst
doc/introduction.rst
doc/make.bat
doc/modules.rst
doc/sparsegrad.base.rst
doc/sparsegrad.forward.rst
doc/sparsegrad.impl.rst
doc/sparsegrad.impl.sparse.rst
doc/sparsegrad.impl.sparsevec.rst
doc/sparsegrad.rst
doc/sparsegrad.sparsevec.rst
doc/timing.rst
doc/tutorial.rst
examples/shallow-water.ipynb
examples/tutorial.ipynb
sparsegrad/__init__.py
sparsegrad/_version.py
sparsegrad.egg-info/PKG-INFO
sparsegrad.egg-info/SOURCES.txt
sparsegrad.egg-info/dependency_links.txt
sparsegrad.egg-info/requires.txt
sparsegrad.egg-info/top_level.txt
sparsegrad/base/__init__.py
sparsegrad/base/expr.py
sparsegrad/forward/__init__.py
sparsegrad/forward/forward.py
sparsegrad/functions/__init__.py
sparsegrad/functions/routing.py
sparsegrad/functions/ufunc.py
sparsegrad/functions/ufunc_routing.py
sparsegrad/functions/utils.py
sparsegrad/impl/__init__.py
sparsegrad/impl/multipledispatch/__init__.py
sparsegrad/impl/multipledispatch/dispatch.py
sparsegrad/impl/sparse/__init__.py
sparsegrad/impl/sparse/sparse.py
sparsegrad/impl/sparsevec/__init__.py
sparsegrad/impl/sparsevec/sparsevec.py
sparsegrad/sparsevec/__init__.py
sparsegrad/sparsevec/routing.py
sparsegrad/sparsevec/sparsevec.py
sparsegrad/testing/__init__.py
sparsegrad/testing/namespaces.py
sparsegrad/testing/test_basic.py
sparsegrad/testing/test_dot.py
sparsegrad/testing/test_indexing.py
sparsegrad/testing/test_sparsity.py
sparsegrad/testing/test_stack.py
sparsegrad/testing/test_sum.py
sparsegrad/testing/test_where.py
sparsegrad/testing/utils.py