Metadata-Version: 1.1
Name: sparsegrad
Version: 0.0.15
Summary: fast calculation of sparse gradients and Jacobian matrices in Python
Home-page: http://www.marekszymanski.com/software/sparsegrad
Author: Marek Zdzislaw Szymanski
Author-email: marek@marekszymanski.com
License: GNU Affero General Public License v3
Platform: any
Classifier: Programming Language :: Python
Classifier: Programming Language :: Python :: 2
Classifier: Programming Language :: Python :: 3
Classifier: Development Status :: 3 - Alpha
Classifier: Natural Language :: English
Classifier: Operating System :: OS Independent
Classifier: Intended Audience :: Science/Research
Classifier: License :: OSI Approved :: GNU Affero General Public License v3
Classifier: Topic :: Scientific/Engineering :: Mathematics
